cusser/__init__.py
cusser/__main__.py
cusser/_misc.py
cusser/color_manager.py
cusser-0.1.0.dist-info/LICENSE
cusser-0.1.0.dist-info/WHEEL
cusser-0.1.0.dist-info/METADATA
cusser-0.1.0.dist-info/RECORD
